cdk_mentor/__init__.py
cdk_mentor/py.typed
cdk_mentor/_jsii/__init__.py
cdk_mentor/_jsii/cdk-mentor@1.1.2.jsii.tgz
cdk_mentor-1.1.2.dist-info/LICENSE
cdk_mentor-1.1.2.dist-info/METADATA
cdk_mentor-1.1.2.dist-info/WHEEL
cdk_mentor-1.1.2.dist-info/top_level.txt
cdk_mentor-1.1.2.dist-info/RECORD
